lektor_envvars.py
lektor_envvars-18.6.12.4.dist-info/METADATA
lektor_envvars-18.6.12.4.dist-info/RECORD
lektor_envvars-18.6.12.4.dist-info/WHEEL
lektor_envvars-18.6.12.4.dist-info/entry_points.txt
lektor_envvars-18.6.12.4.dist-info/top_level.txt
