Metadata-Version: 2.1
Name: lektor-envvars
Version: 18.6.12.4
Summary: A Lektor plugin making environment variables available in templates.
Home-page: https://www.github.com/elbaschid/lektor-envvars
Author: Sebastian Vetter
Author-email: seb@roadsi.de
License: MIT
Platform: UNKNOWN
Classifier: License :: OSI Approved :: MIT License
Classifier: Programming Language :: Python
Classifier: Programming Language :: Python :: 3
Classifier: Programming Language :: Python :: Implementation :: CPython
Requires-Dist: lektor
Requires-Dist: environs
